CHANGES.txt
MANIFEST.in
README.rst
requirements.txt
setup.py
powerfit_scipion/__init__.py
powerfit_scipion/bibtex.py
powerfit_scipion/constants.py
powerfit_scipion/powerfit_logo.png
powerfit_scipion/protocols.conf
powerfit_scipion/wizards.py
powerfit_scipion/protocols/__init__.py
powerfit_scipion/protocols/protocol_powerfit.py
powerfit_scipion/tests/__init__.py
powerfit_scipion/tests/test_powerfit.py
powerfit_scipion/viewers/__init__.py
powerfit_scipion/viewers/viewer_powerfit.py
scipion_em_powerfit.egg-info/PKG-INFO
scipion_em_powerfit.egg-info/SOURCES.txt
scipion_em_powerfit.egg-info/dependency_links.txt
scipion_em_powerfit.egg-info/requires.txt
scipion_em_powerfit.egg-info/top_level.txt