Metadata-Version: 1.0
Name: scipion-em-powerfit
Version: 2.0.1
Summary: Powerfit ready to use in Scipion.
Home-page: https://github.com/scipion-em/scipion-em-powerfit
Author: I2PC, Roberto Marabini and Marta Martinez
Author-email: scipion@cnb.csic.es
License: UNKNOWN
Keywords: scipion cryoem imageprocessing scipion-2
Platform: UNKNOWN
